galois_field/GF.py
galois_field/__init__.py
galois_field/exceptions.py
galois_field/fast_polynom.py
galois_field/util.py
galois_field/tests/__init__.py
galois_field/tests/ffelement_operation_test.py
galois_field/tests/ffelement_test.py
galois_field/tests/gf_test.py
GaloisField-0.1.1.dist-info/LICENSE
GaloisField-0.1.1.dist-info/METADATA
GaloisField-0.1.1.dist-info/WHEEL
GaloisField-0.1.1.dist-info/top_level.txt
GaloisField-0.1.1.dist-info/RECORD
