Metadata-Version: 2.1
Name: GaloisField
Version: 0.1.1
Summary: Galois Finite Field Implementation in Python 3
Home-page: https://github.com/haverzard/GaloisField
Author: haverzard
Author-email: yonatanviody@gmail.com
License: UNKNOWN
Platform: UNKNOWN
Classifier: Programming Language :: Python :: 3
Classifier: License :: OSI Approved :: MIT License
Classifier: Operating System :: OS Independent
Requires-Python: >=3.5
